 {
   "ВыполнитьСценарии": true,
   "ЗавершитьРаботуСистемы": true,
   "ЗакрытьTestClientПослеЗапускаСценариев": true,
   "КаталогФич": "$workspaceRoot/features",
   "КаталогиБиблиотек":[
   "./features/Libraries"
   ],
   "ДелатьОтчетВФорматеАллюр": true,
   "КаталогOutputAllureБазовый": "$workspaceRoot/out/allure",
   "ВыгружатьСтатусВыполненияСценариевВФайл": true,
   "ПутьКФайлуДляВыгрузкиСтатусаВыполненияСценариев": "$workspaceRoot/out/BuildStatus.log",
   "ДелатьОтчетВФорматеCucumberJson": true,
   "КаталогOutputCucumberJson": "$workspaceRoot/out/cucumber"     
}
